{
	"configurations" : 
	[
		{
			"directories" : 
			[
				{
					"build" : ".",
					"hasInstallRule" : true,
					"jsonFile" : "directory-.-7af8941ebf34d53605fc.json",
					"minimumCMakeVersion" : 
					{
						"string" : "3.10.2"
					},
					"projectIndex" : 0,
					"source" : ".",
					"targetIndexes" : 
					[
						0,
						1,
						2,
						3
					]
				}
			],
			"name" : "",
			"projects" : 
			[
				{
					"directoryIndexes" : 
					[
						0
					],
					"name" : "gazebo_maritime",
					"targetIndexes" : 
					[
						0,
						1,
						2,
						3
					]
				}
			],
			"targets" : 
			[
				{
					"directoryIndex" : 0,
					"id" : "PublisherPlugin::@6890427a1f51a3e7e1df",
					"jsonFile" : "target-PublisherPlugin-713d5e0a9ff3a621cc29.json",
					"name" : "PublisherPlugin",
					"projectIndex" : 0
				},
				{
					"directoryIndex" : 0,
					"id" : "Surface::@6890427a1f51a3e7e1df",
					"jsonFile" : "target-Surface-9c59e980b542720ecdf6.json",
					"name" : "Surface",
					"projectIndex" : 0
				},
				{
					"directoryIndex" : 0,
					"id" : "WaveVisual::@6890427a1f51a3e7e1df",
					"jsonFile" : "target-WaveVisual-5333ac4da9b23171d317.json",
					"name" : "WaveVisual",
					"projectIndex" : 0
				},
				{
					"directoryIndex" : 0,
					"id" : "Waves::@6890427a1f51a3e7e1df",
					"jsonFile" : "target-Waves-a3644a0f803b096c1220.json",
					"name" : "Waves",
					"projectIndex" : 0
				}
			]
		}
	],
	"kind" : "codemodel",
	"paths" : 
	{
		"build" : "/home/antoni/gazebo_maritime_ws/build/gazebo_maritime",
		"source" : "/home/antoni/gazebo_maritime_ws/src/gazebo_maritime"
	},
	"version" : 
	{
		"major" : 2,
		"minor" : 6
	}
}
